MANIFEST.in
README.md
setup.py
blockhash/__init__.py
blockhash/constants.py
blockhash/core.py
blockhash/utility.py
blockhash/resources/README.md
blockhash/resources/requirements-testing.txt
blockhash/resources/requirements.txt
blockhash/resources/scripts/blockhash
phash_blockhashio.egg-info/PKG-INFO
phash_blockhashio.egg-info/SOURCES.txt
phash_blockhashio.egg-info/dependency_links.txt
phash_blockhashio.egg-info/requires.txt
phash_blockhashio.egg-info/top_level.txt
test/__init__.py
test/test_blockhash.py
test/command/__init__.py
test/command/test_blockhash.py