Metadata-Version: 2.1
Name: phash-blockhashio
Version: 0.1.4
Summary: Perceptual image hash calculation tool
Home-page: https://github.com/dsoprea/blockhash-python
Author: Commons Machinery
Author-email: dev@commonsmachinery.se
License: MIT
Platform: UNKNOWN
